[

{
	"id": "01",
	"name": "Firebrand",
	"skill1": "29",
	"skill1LV": "2",
	"skill2": "15",
	"skill2LV": "1",
	"slot": "5"

},
{
	"id": "02",
	"name": "Shockjaw",
	"skill1": "02",
	"skill1LV": "2",
	"skill2": "23",
	"skill2LV": "1",
	"slot": "5"

},
{
	"id": "03",
	"name": "Ragetail",
	"skill1": "30",
	"skill1LV": "2",
	"skill2": "37",
	"skill2LV": "1",
	"slot": "3"

	
}
,
{
	"id": "04",
	"name": "Razorwing",
	"skill1": "09",
	"skill1LV": "2",
	"skill2": "14",
	"skill2LV": "1",
	"slot": "2"

}
,
{
	"id": "05",
	"name": "Shrowd",
	"skill1": "29",
	"skill1LV": "2",
	"skill2": "23",
	"skill2LV": "1",
	"slot": "5"

}
,
{
	"id": "06",
	"name": "Rezakiri",
	"skill1": "12",
	"skill1LV": "2",
	"skill2": "06",
	"skill2LV": "1",
	"slot": "4"

},
{
	"id": "07",
	"name": "Pangar",
	"skill1": "20",
	"skill1LV": "2",
	"skill2": "39",
	"skill2LV": "1",
	"slot": "1"

}


]